[{"reservoir":"Grand Coulee/FDR Lake","lat":"47.955833","lng":"-118.981667","state":"WA","pct_capacity":"37","capacity":"9562000","color":"#d7191c"},{"reservoir":"Ross","lat":"48.731667","lng":"-121.067222","state":"WA","pct_capacity":"35.9","capacity":"1404100","color":"#d7191c"},{"reservoir":"Banks Lake","lat":"47.62","lng":"-119.3075","state":"WA","pct_capacity":"0","capacity":"1237000","color":"#d7191c"},{"reservoir":"Lake Chelan","lat":"47.841111","lng":"-120.046389","state":"WA","pct_capacity":"27.7","capacity":"676100","color":"#d7191c"},{"reservoir":"Cle Elum","lat":"47.282","lng":"-121.1075","state":"WA","pct_capacity":"39.1","capacity":"436900","color":"#d7191c"},{"reservoir":"Kachess","lat":"47.264167","lng":"-121.205833","state":"WA","pct_capacity":"65.8","capacity":"239000","color":"#FCE883"},{"reservoir":"Rimrock","lat":"46.656389","lng":"-121.129444","state":"WA","pct_capacity":"46.4","capacity":"198000","color":"#d7191c"},{"reservoir":"Keechelus","lat":"47.3477","lng":"-121.3691","state":"WA","pct_capacity":"56.1","capacity":"157800","color":"#FCE883"},{"reservoir":"Diablo","lat":"48.714167","lng":"-121.13111","state":"WA","pct_capacity":"92.2","capacity":"90600","color":"#1a9641"},{"reservoir":"Bumping Lake","lat":"46.8513","lng":"-121.3193","state":"WA","pct_capacity":"21.7","capacity":"33700","color":"#d7191c"},{"reservoir":"Conconully","lat":"48.53807","lng":"-119.749","state":"WA","pct_capacity":"86.8","capacity":"13000","color":"#1a9641"}]